kida/__init__.py
kida/_types.py
kida/bytecode_cache.py
kida/lexer.py
kida/nodes.py
kida/py.typed
kida/render_accumulator.py
kida/render_context.py
kida/template.py
kida/tstring.py
kida/analysis/__init__.py
kida/analysis/analyzer.py
kida/analysis/cache.py
kida/analysis/config.py
kida/analysis/dependencies.py
kida/analysis/landmarks.py
kida/analysis/metadata.py
kida/analysis/purity.py
kida/analysis/roles.py
kida/compiler/__init__.py
kida/compiler/_protocols.py
kida/compiler/coalescing.py
kida/compiler/core.py
kida/compiler/expressions.py
kida/compiler/utils.py
kida/compiler/statements/__init__.py
kida/compiler/statements/basic.py
kida/compiler/statements/control_flow.py
kida/compiler/statements/functions.py
kida/compiler/statements/special_blocks.py
kida/compiler/statements/template_structure.py
kida/compiler/statements/variables.py
kida/environment/__init__.py
kida/environment/core.py
kida/environment/exceptions.py
kida/environment/filters.py
kida/environment/loaders.py
kida/environment/protocols.py
kida/environment/registry.py
kida/environment/tests.py
kida/parser/__init__.py
kida/parser/_protocols.py
kida/parser/core.py
kida/parser/errors.py
kida/parser/expressions.py
kida/parser/statements.py
kida/parser/tokens.py
kida/parser/blocks/__init__.py
kida/parser/blocks/control_flow.py
kida/parser/blocks/core.py
kida/parser/blocks/functions.py
kida/parser/blocks/special_blocks.py
kida/parser/blocks/template_structure.py
kida/parser/blocks/variables.py
kida/utils/__init__.py
kida/utils/html.py
kida/utils/lru_cache.py
kida/utils/workers.py
kida_templates-0.1.2.dist-info/licenses/LICENSE
kida_templates-0.1.2.dist-info/METADATA
kida_templates-0.1.2.dist-info/WHEEL
kida_templates-0.1.2.dist-info/top_level.txt
kida_templates-0.1.2.dist-info/RECORD
