Metadata-Version: 2.4
Name: kida-templates
Version: 0.1.2
Summary: Modern template engine for Python 3.14t — AST-native, free-threading ready
License-Expression: MIT
Project-URL: Homepage, https://github.com/lbliii/kida
Project-URL: Documentation, https://github.com/lbliii/kida
Project-URL: Repository, https://github.com/lbliii/kida
Project-URL: Changelog, https://github.com/lbliii/kida/blob/main/CHANGELOG.md
Keywords: template-engine,jinja2,free-threading,async,templates
Classifier: Development Status :: 4 - Beta
Classifier: Intended Audience :: Developers
Classifier: Programming Language :: Python :: 3
Classifier: Programming Language :: Python :: 3.14
Classifier: Topic :: Internet :: WWW/HTTP :: Dynamic Content :: CGI Tools/Libraries
Classifier: Topic :: Text Processing :: Markup :: HTML
Classifier: Topic :: Software Development :: Libraries :: Python Modules
Classifier: Typing :: Typed
Requires-Python: >=3.14
License-File: LICENSE
Provides-Extra: docs
Requires-Dist: bengal>=0.1.8; extra == "docs"
Dynamic: license-file
